[
    {
    "id": "1",
    "name": "⛏️ Coal Mines",
    "type": "mining",
    "rarity": "common",
    "spawnWeight": 100,
    "description": "Welcome to the coal mines... yada yada yada yada",
    "power": 1,
    "script": "mining.js",
    "shop": 1,
    "colour": "000000",
    "image": "placeHolder"
    },
    {
    "id": "4",
    "name": "⛏️ Diamond Mines",
    "type": "mining",
    "rarity": "uncommon",
    "spawnWeight": 10,
    "description": "WELCOME TO THE TOPAZ MINES ... yada yada yada yada",
    "power": 3,
    "script": "mining.js",
    "shop": 2,
    "colour": "D69B22",
    "image": "placeHolder"
    },
    {
    "id": "4",
    "name": "⛏️ Topaz Mine",
    "type": "mining",
    "rarity": "rare",
    "spawnWeight": 1,
    "description": "WELCOME TO THE DIAMOND MINES ... yada yada yada yada",
    "power": 3,
    "script": "mining.js",
    "shop": 2,
    "colour": "D69B22",
    "image": "placeHolder"
    }
]